diffsynth_engine/__init__.py
diffsynth_engine/algorithm/__init__.py
diffsynth_engine/algorithm/noise_scheduler/__init__.py
diffsynth_engine/algorithm/noise_scheduler/base_scheduler.py
diffsynth_engine/algorithm/noise_scheduler/flow_match/__init__.py
diffsynth_engine/algorithm/noise_scheduler/flow_match/flow_beta.py
diffsynth_engine/algorithm/noise_scheduler/flow_match/flow_ddim.py
diffsynth_engine/algorithm/noise_scheduler/flow_match/recifited_flow.py
diffsynth_engine/algorithm/noise_scheduler/stable_diffusion/__init__.py
diffsynth_engine/algorithm/noise_scheduler/stable_diffusion/beta.py
diffsynth_engine/algorithm/noise_scheduler/stable_diffusion/ddim.py
diffsynth_engine/algorithm/noise_scheduler/stable_diffusion/exponential.py
diffsynth_engine/algorithm/noise_scheduler/stable_diffusion/karras.py
diffsynth_engine/algorithm/noise_scheduler/stable_diffusion/linear.py
diffsynth_engine/algorithm/noise_scheduler/stable_diffusion/sgm_uniform.py
diffsynth_engine/algorithm/sampler/__init__.py
diffsynth_engine/algorithm/sampler/flow_match/__init__.py
diffsynth_engine/algorithm/sampler/flow_match/flow_match_euler.py
diffsynth_engine/algorithm/sampler/stable_diffusion/__init__.py
diffsynth_engine/algorithm/sampler/stable_diffusion/brownian_tree.py
diffsynth_engine/algorithm/sampler/stable_diffusion/ddpm.py
diffsynth_engine/algorithm/sampler/stable_diffusion/deis.py
diffsynth_engine/algorithm/sampler/stable_diffusion/dpmpp_2m.py
diffsynth_engine/algorithm/sampler/stable_diffusion/dpmpp_2m_sde.py
diffsynth_engine/algorithm/sampler/stable_diffusion/dpmpp_3m_sde.py
diffsynth_engine/algorithm/sampler/stable_diffusion/epsilon.py
diffsynth_engine/algorithm/sampler/stable_diffusion/euler.py
diffsynth_engine/algorithm/sampler/stable_diffusion/euler_ancestral.py
diffsynth_engine/conf/models/components/vae.json
diffsynth_engine/conf/models/flux/flux_dit.json
diffsynth_engine/conf/models/flux/flux_text_encoder.json
diffsynth_engine/conf/models/flux/flux_vae.json
diffsynth_engine-0.6.0.dist-info/licenses/LICENSE
diffsynth_engine-0.6.0.dist-info/METADATA
diffsynth_engine-0.6.0.dist-info/WHEEL
diffsynth_engine-0.6.0.dist-info/top_level.txt
diffsynth_engine-0.6.0.dist-info/RECORD
