Metadata-Version: 2.4
Name: diffsynth_engine
Version: 0.6.0
Author: MuseAI x ModelScope
Classifier: Programming Language :: Python :: 3
Classifier: Operating System :: OS Independent
Requires-Python: >=3.10
License-File: LICENSE
Requires-Dist: torch>=2.6
Requires-Dist: torchvision
Requires-Dist: numpy
Requires-Dist: safetensors
Requires-Dist: gguf
Requires-Dist: einops
Requires-Dist: ftfy
Requires-Dist: regex
Requires-Dist: sentencepiece
Requires-Dist: tokenizers
Requires-Dist: modelscope
Requires-Dist: flufl.lock
Requires-Dist: scipy
Requires-Dist: torchsde
Requires-Dist: pillow
Requires-Dist: imageio[ffmpeg]
Requires-Dist: yunchang; sys_platform == "linux"
Requires-Dist: onnxruntime
Requires-Dist: opencv-python
Requires-Dist: moviepy
Requires-Dist: librosa
Requires-Dist: scikit-image
Requires-Dist: trimesh
Provides-Extra: dev
Requires-Dist: diffusers==0.31.0; extra == "dev"
Requires-Dist: transformers==4.52.4; extra == "dev"
Requires-Dist: accelerate; extra == "dev"
Requires-Dist: build; extra == "dev"
Requires-Dist: ruff; extra == "dev"
Requires-Dist: pytest; extra == "dev"
Requires-Dist: pre-commit; extra == "dev"
Dynamic: license-file
